patcalc/.DS_Store
patcalc/__init__.py
patcalc-0.1.4.dist-info/LICENSE
patcalc-0.1.4.dist-info/WHEEL
patcalc-0.1.4.dist-info/METADATA
patcalc-0.1.4.dist-info/RECORD
